subc/__init__.py
subc/py.typed
subc-0.8.0.dist-info/LICENSE.txt
subc-0.8.0.dist-info/METADATA
subc-0.8.0.dist-info/WHEEL
subc-0.8.0.dist-info/top_level.txt
subc-0.8.0.dist-info/RECORD
