Metadata-Version: 2.1
Name: subc
Version: 0.8.0
Summary: CLI sub-command library
Home-page: https://git.sr.ht/~brenns10/subc
Author: Stephen Brennan
Author-email: stephen@brennan.io
License: Revised BSD
Keywords: arguments sub-command command
Classifier: Development Status :: 3 - Alpha
Classifier: License :: OSI Approved :: BSD License
Classifier: Intended Audience :: Developers
Classifier: Environment :: Console
Classifier: Natural Language :: English
Classifier: Programming Language :: Python :: 3 :: Only
License-File: LICENSE.txt
